DockerComposeLibrary.py
robotframework_docker-1.5.0.dist-info/licenses/LICENSE
robotframework_docker-1.5.0.dist-info/METADATA
robotframework_docker-1.5.0.dist-info/WHEEL
robotframework_docker-1.5.0.dist-info/top_level.txt
robotframework_docker-1.5.0.dist-info/RECORD
